email_mcp/__init__.py
email_mcp/__main__.py
email_mcp/server.py
email_mcp-0.5.0.dist-info/licenses/LICENSE
email_mcp-0.5.0.dist-info/METADATA
email_mcp-0.5.0.dist-info/WHEEL
email_mcp-0.5.0.dist-info/entry_points.txt
email_mcp-0.5.0.dist-info/top_level.txt
email_mcp-0.5.0.dist-info/RECORD
