Metadata-Version: 2.4
Name: email-mcp
Version: 0.5.0
Summary: An MCP server for sending and searching emails
Home-page: https://github.com/mhazarabad/email-mcp
Author: Hadi Azarabad
Author-email: Hadi Azarabad <mhazarabad@gmail.com>
License: MIT License
Project-URL: Homepage, https://github.com/mhazarabad/email-mcp
Project-URL: Repository, https://github.com/mhazarabad/email-mcp.git
Classifier: Programming Language :: Python :: 3
Classifier: License :: OSI Approved :: MIT License
Classifier: Operating System :: OS Independent
Requires-Python: >=3.8
License-File: LICENSE
Requires-Dist: mcp
Dynamic: author
Dynamic: home-page
Dynamic: license-file
Dynamic: requires-python
